{
  "User": "用户",
  "RolePermission": "角色权限",
  "Role": "角色",
  "Team": "项目团队",
  "Permission": "权限",
  "Organization": "组织架构",
  "ThirdPartyIdp": "第三方平台",
  "Position": "职位",
  "SSO": "单点登录",
  "UserClaim": "用户声明",
  "IdentityResource": "身份资源",
  "ApiScope": "Api范围",
  "ApiResource": "Api资源",
  "Client": "客户端",
  "CustomLogin": "自定义登录",
  "OperationLog": "操作日志",
  "ChannelManagement": "渠道管理",
  "MessageManagement": "消息管理",
  "MessageTemplate": "消息模板",
  "ReceiverGroup": "消息组",
  "AlarmRule": "告警规则",
  "AlarmHistory": "告警历史",
  "WebHook": "WebHook"
}
